alexislib/__init__.py
alexislib/modulo.py
alexislib-0.1.2.dist-info/METADATA
alexislib-0.1.2.dist-info/WHEEL
alexislib-0.1.2.dist-info/top_level.txt
alexislib-0.1.2.dist-info/RECORD
